rest_framework_xml/__init__.py
rest_framework_xml/compat.py
rest_framework_xml/parsers.py
rest_framework_xml/renderers.py
djangorestframework_xml-1.4.0.dist-info/LICENSE
djangorestframework_xml-1.4.0.dist-info/METADATA
djangorestframework_xml-1.4.0.dist-info/WHEEL
djangorestframework_xml-1.4.0.dist-info/top_level.txt
djangorestframework_xml-1.4.0.dist-info/RECORD
